bootstrap_mcp/__init__.py
bootstrap_mcp/__main__.py
bootstrap_mcp/server.py
bootstrap_mcp-0.0.7.dist-info/METADATA
bootstrap_mcp-0.0.7.dist-info/WHEEL
bootstrap_mcp-0.0.7.dist-info/entry_points.txt
bootstrap_mcp-0.0.7.dist-info/top_level.txt
bootstrap_mcp-0.0.7.dist-info/RECORD
