Metadata-Version: 2.4
Name: bootstrap-mcp
Version: 0.0.7
Summary: A MCP Server for developers to create startup templates
Requires-Python: >=3.10
Requires-Dist: mcp[cli]
